quant_util/FeatureDaily1.py
quant_util/FeatureDailyClass.py
quant_util/FeatureDailyClassBackup.py
quant_util/FeatureHf.py
quant_util/FeatureHf1.py
quant_util/FeatureHfClass.py
quant_util/__init__.py
quant_util/akshare_api.py
quant_util/calc_feature_pressure_indicator.py
quant_util/calc_feature_trend_indicator.py
quant_util/clickhouse_dao.py
quant_util/config_file.py
quant_util/data_operator.py
quant_util/data_process_MathFun.py
quant_util/local_file_query.py
quant_util/trade_date.py
quant_util/utils.py
quant_util-1.0.5.dist-info/METADATA
quant_util-1.0.5.dist-info/WHEEL
quant_util-1.0.5.dist-info/top_level.txt
quant_util-1.0.5.dist-info/RECORD
