Metadata-Version: 2.1
Name: quant-util
Version: 1.0.5
Summary: local quant-util
Home-page: https://www.python.org/
Author: linzeming
Author-email: linzeming1995@outlook.com
License: MIT
Platform: UNKNOWN
Requires-Python: >=3
